{
    "gender": "W",
    "otAthleteId": "",
    "tpAthleteId": "1062933",
    "birthDate": "1990-11-17",
    "birthYear": "1990",
    "givenName": "Fabienne",
    "familyName": "Schlumpf",
    "height": "183",
    "weight": "62",
    "club": "TG H\u00fctten",
    "nationality": "SUI",
    "birthPlace": null,
    "accomplishments": [
        {
            "eventCode": "CC",
            "rank": "30",
            "ageGroup": "Under 23",
            "competition": "EC",
            "season": "2011"
        },
        {
            "eventCode": "CC",
            "rank": "14",
            "ageGroup": "Under 23",
            "competition": "EC",
            "season": "2012"
        },
        {
            "eventCode": "CC",
            "rank": "37",
            "ageGroup": "Senior",
            "competition": "EC",
            "season": "2013"
        },
        {
            "eventCode": "3000S",
            "rank": "13",
            "ageGroup": "Senior",
            "competition": "EC",
            "season": "2014"
        },
        {
            "eventCode": "CC",
            "rank": "31",
            "ageGroup": "Senior",
            "competition": "EC",
            "season": "2015"
        },
        {
            "eventCode": "3000S",
            "rank": "5",
            "ageGroup": "Senior",
            "competition": "EC",
            "season": "2016"
        },
        {
            "eventCode": "3000S",
            "rank": "18",
            "ageGroup": "Senior",
            "competition": "OG",
            "season": "2016"
        },
        {
            "eventCode": "CC",
            "rank": "8",
            "ageGroup": "Senior",
            "competition": "EC",
            "season": "2016"
        },
        {
            "eventCode": "CC",
            "rank": "7",
            "ageGroup": "Senior",
            "competition": "EC",
            "season": "2017"
        },
        {
            "eventCode": "HM",
            "rank": "16",
            "ageGroup": "Senior",
            "competition": "WC",
            "season": "2018"
        },
        {
            "eventCode": "3000S",
            "rank": "2",
            "ageGroup": "Senior",
            "competition": "EC",
            "season": "2018"
        },
        {
            "eventCode": "CC",
            "rank": "2",
            "ageGroup": "Senior",
            "competition": "EC",
            "season": "2018"
        },
        {
            "eventCode": "HM",
            "rank": "13",
            "ageGroup": "Senior",
            "competition": "WC",
            "season": "2020"
        },
        {
            "eventCode": "Mar",
            "rank": "12",
            "ageGroup": "Senior",
            "competition": "OG",
            "season": "2021"
        },
        {
            "eventCode": "Mar",
            "rank": "9",
            "ageGroup": "Senior",
            "competition": "EC",
            "season": "2022"
        },
        {
            "eventCode": "HM",
            "rank": "7",
            "ageGroup": "Senior",
            "competition": "EC",
            "season": "2024"
        },
        {
            "eventCode": "Mar",
            "rank": "16",
            "ageGroup": "Senior",
            "competition": "OG",
            "season": "2024"
        }
    ],
    "personalBests": [
        {
            "eventCode": "MileR",
            "performance": "4:47",
            "iaafpoints": "1000",
            "wind": "",
            "rank": "5",
            "roundDetail": "",
            "round": "Final",
            "ageGroup": "",
            "tpCompId": "12854277",
            "compName": "Jungfrau Mile",
            "date": "2014-09-12",
            "city": "Interlaken",
            "country": "SUI"
        },
        {
            "indoor": true,
            "eventCode": "3000",
            "performance": "9:34.44",
            "iaafpoints": "1013",
            "wind": "",
            "rank": "1",
            "roundDetail": "",
            "round": "Final",
            "ageGroup": "",
            "tpCompId": "12870351",
            "compName": "National Indoor Championships",
            "date": "2016-02-28",
            "city": "St. Gallen",
            "country": "SUI"
        },
        {
            "eventCode": "2000S",
            "performance": "6:20.33",
            "iaafpoints": "1106",
            "wind": "",
            "rank": "1",
            "roundDetail": "",
            "round": "Final",
            "ageGroup": "",
            "tpCompId": "12893265",
            "compName": "27. Internationales L\u00e4ufermeeting",
            "date": "2017-05-14",
            "city": "Pliezhausen",
            "country": "GER"
        },
        {
            "eventCode": "3000S",
            "performance": "9:21.65",
            "iaafpoints": "1189",
            "wind": "",
            "rank": "3",
            "roundDetail": "",
            "round": "Final",
            "ageGroup": "",
            "tpCompId": "12894847",
            "compName": "Bislett Games, IAAF Diamond League, Bislett Stadium",
            "date": "2017-06-15",
            "city": "Oslo",
            "country": "NOR"
        },
        {
            "eventCode": "3000",
            "performance": "8:58.63",
            "iaafpoints": "1110",
            "wind": "",
            "rank": "7",
            "roundDetail": "",
            "round": "Final",
            "ageGroup": "",
            "tpCompId": "12898045",
            "compName": "Spitzen Leichtathletik, Stadion Allmend",
            "date": "2017-07-11",
            "city": "Luzern",
            "country": "SUI"
        },
        {
            "eventCode": "800",
            "performance": "2:12.07",
            "iaafpoints": "956",
            "wind": "",
            "rank": "1",
            "roundDetail": "h3",
            "round": "Prelim",
            "ageGroup": "",
            "tpCompId": "12898418",
            "compName": "National Championships",
            "date": "2017-07-21",
            "city": "Z\u00fcrich",
            "country": "SUI"
        },
        {
            "eventCode": "5000",
            "performance": "15:23.44",
            "iaafpoints": "1118",
            "wind": "",
            "rank": "5",
            "roundDetail": "",
            "round": "Final",
            "ageGroup": "",
            "tpCompId": "12910726",
            "compName": "Gal\u00e0 dei Castelli, Stadio Comunale",
            "date": "2018-07-18",
            "city": "Bellinzona",
            "country": "SUI"
        },
        {
            "eventCode": "10K",
            "performance": "32:01",
            "iaafpoints": "1138",
            "wind": "",
            "rank": "3",
            "roundDetail": "",
            "round": "Final",
            "ageGroup": "",
            "tpCompId": "12912690",
            "compName": "Bridgestone Great 10K Berlin",
            "date": "2018-10-14",
            "city": "Berlin",
            "country": "GER"
        },
        {
            "eventCode": "1500",
            "performance": "4:14.29",
            "iaafpoints": "1093",
            "wind": "",
            "rank": "1",
            "roundDetail": "",
            "round": "Final",
            "ageGroup": "",
            "tpCompId": "12970465",
            "compName": "SM Aktive",
            "date": "2020-09-12",
            "city": "Basel",
            "country": "SUI"
        },
        {
            "eventCode": "HM",
            "performance": "1:08:27",
            "iaafpoints": "1162",
            "wind": "",
            "rank": "1",
            "roundDetail": "",
            "round": "Final",
            "ageGroup": "",
            "tpCompId": "12978382",
            "compName": "itelligence Citylauf Invitational",
            "date": "2021-03-21",
            "city": "Dresden",
            "country": "GER"
        },
        {
            "eventCode": "10000",
            "performance": "33:13.63",
            "iaafpoints": "1075",
            "wind": "",
            "rank": "1",
            "roundDetail": "",
            "round": "Final",
            "ageGroup": "",
            "tpCompId": "12988096",
            "compName": "SM 10'000m und Steeple",
            "date": "2021-06-04",
            "city": "Uster",
            "country": "SUI"
        },
        {
            "eventCode": "5K",
            "performance": "15:47",
            "iaafpoints": "1074",
            "wind": "",
            "rank": "7",
            "roundDetail": "",
            "round": "Final",
            "ageGroup": "",
            "tpCompId": "13024808",
            "compName": "Course de No\u00ebl",
            "date": "2022-12-10",
            "city": "Sion",
            "country": "SUI"
        },
        {
            "eventCode": "Mar",
            "performance": "2:24:30",
            "iaafpoints": "1169",
            "wind": "",
            "rank": "13",
            "roundDetail": "",
            "round": "Final",
            "ageGroup": "",
            "tpCompId": "13050767",
            "compName": "Maraton Valencia Trinidad Alfonso",
            "date": "2023-12-03",
            "city": "Valencia",
            "country": "ESP"
        },
        {
            "eventCode": "10M",
            "performance": "54:31",
            "iaafpoints": "1076",
            "wind": "",
            "rank": "1",
            "roundDetail": "",
            "round": "Final",
            "ageGroup": "",
            "tpCompId": "13088073",
            "compName": "Grand-Prix von Bern",
            "date": "2024-05-18",
            "city": "Bern",
            "country": "SUI"
        }
    ],
    "results": [
        {
            "IndoorOutdoor": "Outdoor",
            "event": "2000S",
            "okForSB": true,
            "result": "7:06.28",
            "iaafpoints": "929",
            "wind": "",
            "rank": "8",
            "round": "",
            "roundstage": "Final",
            "agegroup": "",
            "competition_ID": "11788947",
            "compName": null,
            "compShort": null,
            "date": "2008-05-18",
            "city": "Pliezhausen",
            "venuecountry": "GER"
        },
        {
            "IndoorOutdoor": "Outdoor",
            "event": "3000S",
            "okForSB": true,
            "result": "11:06.79",
            "iaafpoints": "940",
            "wind": "",
            "rank": "2",
            "round": "",
            "roundstage": "Final",
            "agegroup": "",
            "competition_ID": "12018279",
            "compName": null,
            "compShort": "NC",
            "date": "2008-08-02",
            "city": "Fribourg",
            "venuecountry": "SUI"
        },
        {
            "IndoorOutdoor": "Outdoor",
            "event": "3000S",
            "okForSB": true,
            "result": "10:57.74",
            "iaafpoints": "960",
            "wind": "",
            "rank": "1",
            "round": "",
            "roundstage": "Final",
            "agegroup": "",
            "competition_ID": "12788128",
            "compName": null,
            "compShort": null,
            "date": "2009-06-25",
            "city": "Regensdorf",
            "venuecountry": "SUI"
        },
        {
            "IndoorOutdoor": "Outdoor",
            "event": "3000S",
            "okForSB": true,
            "result": "11:19.84",
            "iaafpoints": "911",
            "wind": "",
            "rank": "11",
            "round": "h1-19",
            "roundstage": "Prelim",
            "agegroup": "",
            "competition_ID": "12788872",
            "compName": "20nd European Athletics Junior Championships",
            "compShort": "EJ",
            "date": "2009-07-23",
            "city": "Novi Sad",
            "venuecountry": "SRB"
        },
        {
            "IndoorOutdoor": "Outdoor",
            "event": "3000S",
            "okForSB": true,
            "result": "11:20.48",
            "iaafpoints": "910",
            "wind": "",
            "rank": "1",
            "round": "",
            "roundstage": "Final",
            "agegroup": "",
            "competition_ID": "12789008",
            "compName": null,
            "compShort": "NC",
            "date": "2009-08-01",
            "city": "Z\u00fcrich",
            "venuecountry": "SUI"
        },
        {
            "IndoorOutdoor": "Outdoor",
            "event": "2000S",
            "okForSB": true,
            "result": "6:53.91",
            "iaafpoints": "975",
            "wind": "",
            "rank": "8",
            "round": "",
            "roundstage": "Final",
            "agegroup": "",
            "competition_ID": "12796921",
            "compName": null,
            "compShort": null,
            "date": "2010-05-16",
            "city": "Pliezhausen",
            "venuecountry": "GER"
        },
        {
            "IndoorOutdoor": "Outdoor",
            "event": "3000S",
            "okForSB": true,
            "result": "10:51.77",
            "iaafpoints": "974",
            "wind": "",
            "rank": "4",
            "round": "-22",
            "roundstage": "Final",
            "agegroup": "Under 23",
            "competition_ID": "12798976",
            "compName": null,
            "compShort": "v2Nat",
            "date": "2010-06-26",
            "city": "Heilbronn",
            "venuecountry": "GER"
        },
        {
            "IndoorOutdoor": "Outdoor",
            "event": "2000S",
            "okForSB": true,
            "result": "6:34.78",
            "iaafpoints": "1049",
            "wind": "",
            "rank": "1",
            "round": "",
            "roundstage": "Final",
            "agegroup": "",
            "competition_ID": "12810429",
            "compName": "21st Internationales L\u00e4ufermeeting, Sch\u00f6nbuchstadion",
            "compShort": null,
            "date": "2011-05-22",
            "city": "Pliezhausen",
            "venuecountry": "GER"
        },
        {
            "IndoorOutdoor": "Outdoor",
            "event": "5000",
            "okForSB": true,
            "result": "16:48.89",
            "iaafpoints": "961",
            "wind": "",
            "rank": "16",
            "round": "",
            "roundstage": "Final",
            "agegroup": "",
            "competition_ID": "12810578",
            "compName": "Mini-Internationales",
            "compShort": null,
            "date": "2011-05-25",
            "city": "Koblenz",
            "venuecountry": "GER"
        },
        {
            "IndoorOutdoor": "Outdoor",
            "event": "3000S",
            "okForSB": true,
            "result": "10:22.27",
            "iaafpoints": "1042",
            "wind": "",
            "rank": "8",
            "round": "",
            "roundstage": "Final",
            "agegroup": "",
            "competition_ID": "12811063",
            "compName": "Sparkassen Gala, Universit\u00e4tsstadion",
            "compShort": "Sparkassen",
            "date": "2011-06-04",
            "city": "Regensburg",
            "venuecountry": "GER"
        },
        {
            "IndoorOutdoor": "Outdoor",
            "event": "3000S",
            "okForSB": true,
            "result": "10:33.67",
            "iaafpoints": "1016",
            "wind": "",
            "rank": "7",
            "round": "",
            "roundstage": "Final",
            "agegroup": "",
            "competition_ID": "12811806",
            "compName": "3rd European Team Championships, First League",
            "compShort": "ETC-1",
            "date": "2011-06-18",
            "city": "Izmir",
            "venuecountry": "TUR"
        },
        {
            "IndoorOutdoor": "Outdoor",
            "event": "1500",
            "okForSB": true,
            "result": "4:29.31",
            "iaafpoints": "981",
            "wind": "",
            "rank": "3",
            "round": "",
            "roundstage": "Final",
            "agegroup": "",
            "competition_ID": "12812887",
            "compName": null,
            "compShort": "Bonus-Track",
            "date": "2011-07-09",
            "city": "Hochdorf",
            "venuecountry": "SUI"
        },
        {
            "IndoorOutdoor": "Outdoor",
            "event": "3000S",
            "okForSB": true,
            "result": "10:31.10",
            "iaafpoints": "1021",
            "wind": "",
            "rank": "7",
            "round": "h1-22",
            "roundstage": "Prelim",
            "agegroup": "",
            "competition_ID": "12813128",
            "compName": "8th European Athletics U23 Championships",
            "compShort": "EJ",
            "date": "2011-07-14",
            "city": "Ostrava",
            "venuecountry": "CZE"
        },
        {
            "IndoorOutdoor": "Outdoor",
            "event": "1500",
            "okForSB": true,
            "result": "4:29.58",
            "iaafpoints": "979",
            "wind": "",
            "rank": "4",
            "round": "",
            "roundstage": "Final",
            "agegroup": "",
            "competition_ID": "12813772",
            "compName": "Schweizer Leichtathletik-Meisterschaften, Stadion Sch\u00fctzenmatte",
            "compShort": "NC",
            "date": "2011-08-06",
            "city": "Basel",
            "venuecountry": "SUI"
        },
        {
            "IndoorOutdoor": "Outdoor",
            "event": "CC",
            "okForSB": true,
            "result": "29:36",
            "iaafpoints": "",
            "wind": "",
            "rank": "18",
            "round": "",
            "roundstage": "Final",
            "agegroup": "",
            "competition_ID": "12817126",
            "compName": "International loket.nl Warandecross",
            "compShort": "Warandecross",
            "date": "2011-11-27",
            "city": "Tilburg",
            "venuecountry": "NED"
        },
        {
            "IndoorOutdoor": "Outdoor",
            "event": "CC",
            "okForSB": true,
            "result": "21:31",
            "iaafpoints": "",
            "wind": "",
            "rank": "30",
            "round": "-22",
            "roundstage": "Final",
            "agegroup": "Under 23",
            "competition_ID": "12817665",
            "compName": "18th European Cross Country Championships",
            "compShort": "EC",
            "date": "2011-12-11",
            "city": "Velenje",
            "venuecountry": "SLO"
        },
        {
            "IndoorOutdoor": "Outdoor",
            "event": "2000S",
            "okForSB": true,
            "result": "6:30.96",
            "iaafpoints": "1064",
            "wind": "",
            "rank": "2",
            "round": "",
            "roundstage": "Final",
            "agegroup": "",
            "competition_ID": "12822705",
            "compName": null,
            "compShort": null,
            "date": "2012-05-06",
            "city": "Pliezhausen",
            "venuecountry": "GER"
        },
        {
            "IndoorOutdoor": "Outdoor",
            "event": "3000",
            "okForSB": true,
            "result": "9:40.33",
            "iaafpoints": "974",
            "wind": "",
            "rank": "1",
            "round": "",
            "roundstage": "Final",
            "agegroup": "",
            "competition_ID": "12822971",
            "compName": null,
            "compShort": null,
            "date": "2012-05-17",
            "city": "Langenthal",
            "venuecountry": "SUI"
        },
        {
            "IndoorOutdoor": "Outdoor",
            "event": "5000",
            "okForSB": true,
            "result": "16:30.23",
            "iaafpoints": "995",
            "wind": "",
            "rank": "10",
            "round": "",
            "roundstage": "Final",
            "agegroup": "",
            "competition_ID": "12823081",
            "compName": "30th Rot-Wei\u00df Koblenz Mini-Internationales",
            "compShort": "Mini-Int",
            "date": "2012-05-23",
            "city": "Koblenz",
            "venuecountry": "GER"
        },
        {
            "IndoorOutdoor": "Outdoor",
            "event": "3000S",
            "okForSB": true,
            "result": "9:55.50",
            "iaafpoints": "1106",
            "wind": "",
            "rank": "1",
            "round": "",
            "roundstage": "Final",
            "agegroup": "",
            "competition_ID": "12823488",
            "compName": "Sparkassen Gala",
            "compShort": "Sparkassen",
            "date": "2012-06-02",
            "city": "Regensburg",
            "venuecountry": "GER"
        },
        {
            "IndoorOutdoor": "Outdoor",
            "event": "3000S",
            "okForSB": true,
            "result": "10:15.38",
            "iaafpoints": "1058",
            "wind": "",
            "rank": "8",
            "round": "",
            "roundstage": "Final",
            "agegroup": "",
            "competition_ID": "12823711",
            "compName": "19th Josef Odlo\u017eil Memorial",
            "compShort": "Odlozil",
            "date": "2012-06-11",
            "city": "Praha",
            "venuecountry": "CZE"
        },
        {
            "IndoorOutdoor": "Outdoor",
            "event": "3000S",
            "okForSB": true,
            "result": "10:09.98",
            "iaafpoints": "1071",
            "wind": "",
            "rank": "1",
            "round": "",
            "roundstage": "Final",
            "agegroup": "",
            "competition_ID": "12827320",
            "compName": null,
            "compShort": null,
            "date": "2012-06-22",
            "city": "Uster",
            "venuecountry": "SUI"
        },
        {
            "IndoorOutdoor": "Outdoor",
            "event": "5000",
            "okForSB": true,
            "result": "16:41.36",
            "iaafpoints": "975",
            "wind": "",
            "rank": "1",
            "round": "-22",
            "roundstage": "Final",
            "agegroup": "Under 23",
            "competition_ID": "12825757",
            "compName": "NC U20/23",
            "compShort": "NC-j",
            "date": "2012-09-08",
            "city": "Basel",
            "venuecountry": "SUI"
        },
        {
            "IndoorOutdoor": "Outdoor",
            "event": "CC",
            "okForSB": true,
            "result": "21:44",
            "iaafpoints": "",
            "wind": "",
            "rank": "1",
            "round": "-19",
            "roundstage": "Final",
            "agegroup": "Under 20",
            "competition_ID": "12826750",
            "compName": "Sparkassen Cross Pforzheim",
            "compShort": "Sparkassen",
            "date": "2012-11-10",
            "city": "Pforzheim",
            "venuecountry": "GER"
        },
        {
            "IndoorOutdoor": "Outdoor",
            "event": "CC",
            "okForSB": true,
            "result": "24:26",
            "iaafpoints": "",
            "wind": "",
            "rank": "1",
            "round": "",
            "roundstage": "Final",
            "agegroup": "",
            "competition_ID": "12826786",
            "compName": "Darmstadt-Cross",
            "compShort": null,
            "date": "2012-11-25",
            "city": "Darmstadt",
            "venuecountry": "GER"
        },
        {
            "IndoorOutdoor": "Outdoor",
            "event": "CC",
            "okForSB": true,
            "result": "21:32",
            "iaafpoints": "",
            "wind": "",
            "rank": "14",
            "round": "-22",
            "roundstage": "Final",
            "agegroup": "Under 23",
            "competition_ID": "12826928",
            "compName": "19th European Cross Country Championships",
            "compShort": "EC",
            "date": "2012-12-09",
            "city": "Budapest",
            "venuecountry": "HUN"
        },
        {
            "IndoorOutdoor": "Outdoor",
            "event": "RR",
            "okForSB": true,
            "result": "20:58",
            "iaafpoints": "",
            "wind": "",
            "rank": "4",
            "round": "",
            "roundstage": "Final",
            "agegroup": "",
            "competition_ID": "12827243",
            "compName": "Silvesterlauf Z\u00fcrich",
            "compShort": null,
            "date": "2012-12-16",
            "city": "Z\u00fcrich",
            "venuecountry": "SUI"
        },
        {
            "IndoorOutdoor": "Outdoor",
            "event": "CC",
            "okForSB": true,
            "result": "22:00",
            "iaafpoints": "",
            "wind": "",
            "rank": "10",
            "round": "",
            "roundstage": "Final",
            "agegroup": "",
            "competition_ID": "12828144",
            "compName": "Lotto CrossCup Brussels",
            "compShort": null,
            "date": "2012-12-23",
            "city": "Bruxelles",
            "venuecountry": "BEL"
        },
        {
            "IndoorOutdoor": "Outdoor",
            "event": "10K",
            "okForSB": true,
            "result": "34:02",
            "iaafpoints": "1034",
            "wind": "",
            "rank": "1",
            "round": "",
            "roundstage": "Final",
            "agegroup": "",
            "competition_ID": "12840208",
            "compName": "Swiss 10-K Championships",
            "compShort": "NC",
            "date": "2013-03-23",
            "city": "Uster",
            "venuecountry": "SUI"
        },
        {
            "IndoorOutdoor": "Outdoor",
            "event": "5000",
            "okForSB": true,
            "result": "16:01.52",
            "iaafpoints": "1047",
            "wind": "",
            "rank": "3",
            "round": "",
            "roundstage": "Final",
            "agegroup": "",
            "competition_ID": "12841566",
            "compName": "Mini-Internationales",
            "compShort": null,
            "date": "2013-05-15",
            "city": "Koblenz",
            "venuecountry": "GER"
        },
        {
            "IndoorOutdoor": "Outdoor",
            "event": "3000S",
            "okForSB": true,
            "result": "9:48.45",
            "iaafpoints": "1123",
            "wind": "",
            "rank": "1",
            "round": "",
            "roundstage": "Final",
            "agegroup": "",
            "competition_ID": "12841923",
            "compName": "IFAM Outdoor",
            "compShort": "IFAM",
            "date": "2013-06-01",
            "city": "Oordegem",
            "venuecountry": "BEL"
        },
        {
            "IndoorOutdoor": "Outdoor",
            "event": "3000S",
            "okForSB": true,
            "result": "10:02.39",
            "iaafpoints": "1089",
            "wind": "",
            "rank": "3",
            "round": "",
            "roundstage": "Final",
            "agegroup": "",
            "competition_ID": "12842123",
            "compName": "Meeting National de Montb\u00e9liard",
            "compShort": null,
            "date": "2013-06-06",
            "city": "Montb\u00e9liard",
            "venuecountry": "FRA"
        },
        {
            "IndoorOutdoor": "Outdoor",
            "event": "3000S",
            "okForSB": true,
            "result": "10:01.88",
            "iaafpoints": "1091",
            "wind": "",
            "rank": "7",
            "round": "",
            "roundstage": "Final",
            "agegroup": "",
            "competition_ID": "12842928",
            "compName": "4th European Team Championships, First League",
            "compShort": "ETC-1",
            "date": "2013-06-22",
            "city": "Dublin",
            "venuecountry": "IRL"
        },
        {
            "IndoorOutdoor": "Outdoor",
            "event": "3000S",
            "okForSB": true,
            "result": "9:46.98",
            "iaafpoints": "1127",
            "wind": "",
            "rank": "2",
            "round": "",
            "roundstage": "Final",
            "agegroup": "",
            "competition_ID": "12843752",
            "compName": "7th Bottrop Gala, Jahnstadion",
            "compShort": null,
            "date": "2013-07-19",
            "city": "Bottrop",
            "venuecountry": "GER"
        },
        {
            "IndoorOutdoor": "Outdoor",
            "event": "1500",
            "okForSB": true,
            "result": "4:26.35",
            "iaafpoints": "1003",
            "wind": "",
            "rank": "2",
            "round": "",
            "roundstage": "Final",
            "agegroup": "",
            "competition_ID": "12843826",
            "compName": null,
            "compShort": "NC",
            "date": "2013-07-27",
            "city": "Luzern",
            "venuecountry": "SUI"
        },
        {
            "IndoorOutdoor": "Outdoor",
            "event": "3000S",
            "okForSB": false,
            "result": "",
            "iaafpoints": "",
            "wind": "",
            "rank": "",
            "round": "h2",
            "roundstage": "Prelim",
            "agegroup": "",
            "competition_ID": "12844203",
            "compName": "14th IAAF World Championships",
            "compShort": "WC",
            "date": "2013-08-10",
            "city": "Moskva",
            "venuecountry": "RUS"
        },
        {
            "IndoorOutdoor": "Outdoor",
            "event": "10K",
            "okForSB": true,
            "result": "33:16",
            "iaafpoints": "1073",
            "wind": "",
            "rank": "3",
            "round": "",
            "roundstage": "Final",
            "agegroup": "",
            "competition_ID": "12845027",
            "compName": "ASICS Grand 10 Berlin",
            "compShort": "Asics",
            "date": "2013-10-13",
            "city": "Berlin",
            "venuecountry": "GER"
        },
        {
            "IndoorOutdoor": "Outdoor",
            "event": "CC",
            "okForSB": true,
            "result": "15:59",
            "iaafpoints": "",
            "wind": "",
            "rank": "2",
            "round": "",
            "roundstage": "Final",
            "agegroup": "",
            "competition_ID": "12845275",
            "compName": "Lotto CrossCup van de Provincie Antwerpen",
            "compShort": "Lotto",
            "date": "2013-11-03",
            "city": "Mol",
            "venuecountry": "BEL"
        },
        {
            "IndoorOutdoor": "Outdoor",
            "event": "CC",
            "okForSB": true,
            "result": "28:21",
            "iaafpoints": "",
            "wind": "",
            "rank": "7",
            "round": "",
            "roundstage": "Final",
            "agegroup": "",
            "competition_ID": "12845545",
            "compName": null,
            "compShort": "Warandeloop",
            "date": "2013-11-24",
            "city": "Tilburg",
            "venuecountry": "NED"
        },
        {
            "IndoorOutdoor": "Outdoor",
            "event": "CC",
            "okForSB": true,
            "result": "28:15",
            "iaafpoints": "",
            "wind": "",
            "rank": "37",
            "round": "",
            "roundstage": "Final",
            "agegroup": "",
            "competition_ID": "12845745",
            "compName": "20th European Cross Country Championships",
            "compShort": "EC",
            "date": "2013-12-08",
            "city": "Beograd",
            "venuecountry": "SRB"
        },
        {
            "IndoorOutdoor": "Outdoor",
            "event": "CC",
            "okForSB": true,
            "result": "20:27",
            "iaafpoints": "",
            "wind": "",
            "rank": "5",
            "round": "",
            "roundstage": "Final",
            "agegroup": "",
            "competition_ID": "12846496",
            "compName": "Lotto CrossCup Brussels",
            "compShort": null,
            "date": "2013-12-22",
            "city": "Bruxelles",
            "venuecountry": "BEL"
        },
        {
            "IndoorOutdoor": "Outdoor",
            "event": "RR",
            "okForSB": true,
            "result": "13:45",
            "iaafpoints": "",
            "wind": "",
            "rank": "7",
            "round": "",
            "roundstage": "Final",
            "agegroup": "",
            "competition_ID": "12849922",
            "compName": "Luzerner Stadtlauf",
            "compShort": "Stadtlauf",
            "date": "2014-05-03",
            "city": "Luzern",
            "venuecountry": "SUI"
        },
        {
            "IndoorOutdoor": "Outdoor",
            "event": "5000",
            "okForSB": true,
            "result": "16:30.91",
            "iaafpoints": "993",
            "wind": "",
            "rank": "1",
            "round": "",
            "roundstage": "Final",
            "agegroup": "",
            "competition_ID": "12851933",
            "compName": null,
            "compShort": null,
            "date": "2014-05-07",
            "city": "Karlsfeld",
            "venuecountry": "GER"
        },
        {
            "IndoorOutdoor": "Outdoor",
            "event": "3000",
            "okForSB": false,
            "result": "9:13.06",
            "iaafpoints": "",
            "wind": "",
            "rank": "1",
            "round": "",
            "roundstage": "Final",
            "agegroup": "",
            "competition_ID": "12851428",
            "compName": "Auffahrtsmeeting",
            "compShort": null,
            "date": "2014-05-29",
            "city": "Langenthal",
            "venuecountry": "SUI"
        },
        {
            "IndoorOutdoor": "Outdoor",
            "event": "3000S",
            "okForSB": true,
            "result": "9:37.81",
            "iaafpoints": "1149",
            "wind": "",
            "rank": "3",
            "round": "",
            "roundstage": "Final",
            "agegroup": "",
            "competition_ID": "12851454",
            "compName": "IFAM Outdoor",
            "compShort": "IFAM",
            "date": "2014-05-31",
            "city": "Oordegem",
            "venuecountry": "BEL"
        },
        {
            "IndoorOutdoor": "Outdoor",
            "event": "3000S",
            "okForSB": true,
            "result": "9:56.71",
            "iaafpoints": "1103",
            "wind": "",
            "rank": "5",
            "round": "",
            "roundstage": "Final",
            "agegroup": "",
            "competition_ID": "12851720",
            "compName": "50th Internationales Pfingstsportfest, Bungertstadion",
            "compShort": "Pfingst",
            "date": "2014-06-09",
            "city": "Rehlingen",
            "venuecountry": "GER"
        },
        {
            "IndoorOutdoor": "Outdoor",
            "event": "3000",
            "okForSB": true,
            "result": "9:14.89",
            "iaafpoints": "1056",
            "wind": "",
            "rank": "2",
            "round": "",
            "roundstage": "Final",
            "agegroup": "",
            "competition_ID": "12852379",
            "compName": "5th European Athletics Team Championships, Second League, Daugava Stadium",
            "compShort": "ETC-2",
            "date": "2014-06-21",
            "city": "R\u012bga",
            "venuecountry": "LAT"
        },
        {
            "IndoorOutdoor": "Outdoor",
            "event": "5000",
            "okForSB": true,
            "result": "15:51.06",
            "iaafpoints": "1066",
            "wind": "",
            "rank": "1",
            "round": "",
            "roundstage": "Final",
            "agegroup": "",
            "competition_ID": "12852379",
            "compName": "5th European Athletics Team Championships, Second League, Daugava Stadium",
            "compShort": "ETC-2",
            "date": "2014-06-22",
            "city": "R\u012bga",
            "venuecountry": "LAT"
        },
        {
            "IndoorOutdoor": "Outdoor",
            "event": "1500",
            "okForSB": true,
            "result": "4:23.94",
            "iaafpoints": "1021",
            "wind": "",
            "rank": "1",
            "round": "h1",
            "roundstage": "Prelim",
            "agegroup": "",
            "competition_ID": "12853394",
            "compName": "National Championships",
            "compShort": "NC",
            "date": "2014-07-25",
            "city": "Frauenfeld",
            "venuecountry": "SUI"
        },
        {
            "IndoorOutdoor": "Outdoor",
            "event": "1500",
            "okForSB": true,
            "result": "4:22.89",
            "iaafpoints": "1028",
            "wind": "",
            "rank": "1",
            "round": "",
            "roundstage": "Final",
            "agegroup": "",
            "competition_ID": "12853394",
            "compName": "National Championships",
            "compShort": "NC",
            "date": "2014-07-26",
            "city": "Frauenfeld",
            "venuecountry": "SUI"
        },
        {
            "IndoorOutdoor": "Outdoor",
            "event": "3000S",
            "okForSB": true,
            "result": "9:51.45",
            "iaafpoints": "1116",
            "wind": "",
            "rank": "5",
            "round": "h1",
            "roundstage": "Prelim",
            "agegroup": "",
            "competition_ID": "12853650",
            "compName": "22nd European Athletics Championships",
            "compShort": "EC",
            "date": "2014-08-15",
            "city": "Z\u00fcrich",
            "venuecountry": "SUI"
        },
        {
            "IndoorOutdoor": "Outdoor",
            "event": "3000S",
            "okForSB": true,
            "result": "9:55.92",
            "iaafpoints": "1105",
            "wind": "",
            "rank": "13",
            "round": "",
            "roundstage": "Final",
            "agegroup": "",
            "competition_ID": "12853650",
            "compName": "22nd European Athletics Championships",
            "compShort": "EC",
            "date": "2014-08-17",
            "city": "Z\u00fcrich",
            "venuecountry": "SUI"
        },
        {
            "IndoorOutdoor": "Outdoor",
            "event": "MileR",
            "okForSB": true,
            "result": "4:47",
            "iaafpoints": "1000",
            "wind": "",
            "rank": "5",
            "round": "",
            "roundstage": "Final",
            "agegroup": "",
            "competition_ID": "12854277",
            "compName": "Jungfrau Mile",
            "compShort": null,
            "date": "2014-09-12",
            "city": "Interlaken",
            "venuecountry": "SUI"
        },
        {
            "IndoorOutdoor": "Outdoor",
            "event": "10K",
            "okForSB": true,
            "result": "33:36",
            "iaafpoints": "1056",
            "wind": "",
            "rank": "6",
            "round": "",
            "roundstage": "Final",
            "agegroup": "",
            "competition_ID": "12854682",
            "compName": "ASICS Grand 10",
            "compShort": null,
            "date": "2014-10-12",
            "city": "Berlin",
            "venuecountry": "GER"
        },
        {
            "IndoorOutdoor": "Outdoor",
            "event": "HM",
            "okForSB": true,
            "result": "1:14:53",
            "iaafpoints": "1031",
            "wind": "",
            "rank": "1",
            "round": "",
            "roundstage": "Final",
            "agegroup": "",
            "competition_ID": "12854896",
            "compName": "SwissCity Marathon",
            "compShort": null,
            "date": "2014-10-26",
            "city": "Luzern",
            "venuecountry": "SUI"
        },
        {
            "IndoorOutdoor": "Outdoor",
            "event": "RR",
            "okForSB": true,
            "result": "20:38",
            "iaafpoints": "",
            "wind": "",
            "rank": "4",
            "round": "",
            "roundstage": "Final",
            "agegroup": "",
            "competition_ID": "12855088",
            "compName": "La Corrida Bulloise",
            "compShort": null,
            "date": "2014-11-15",
            "city": "Bulle",
            "venuecountry": "SUI"
        },
        {
            "IndoorOutdoor": "Outdoor",
            "event": "RR",
            "okForSB": true,
            "result": "19:24",
            "iaafpoints": "",
            "wind": "",
            "rank": "1",
            "round": "",
            "roundstage": "Final",
            "agegroup": "",
            "competition_ID": "12855419",
            "compName": "Basler Stadtlauf",
            "compShort": "Stadtlauf",
            "date": "2014-11-29",
            "city": "Basel",
            "venuecountry": "SUI"
        },
        {
            "IndoorOutdoor": "Outdoor",
            "event": "RR",
            "okForSB": true,
            "result": "21:29",
            "iaafpoints": "",
            "wind": "",
            "rank": "2",
            "round": "",
            "roundstage": "Final",
            "agegroup": "",
            "competition_ID": "12855435",
            "compName": "Silvesterlauf Z\u00fcrich",
            "compShort": null,
            "date": "2014-12-14",
            "city": "Z\u00fcrich",
            "venuecountry": "SUI"
        },
        {
            "IndoorOutdoor": "Outdoor",
            "event": "CC",
            "okForSB": true,
            "result": "21:40",
            "iaafpoints": "",
            "wind": "",
            "rank": "9",
            "round": "",
            "roundstage": "Final",
            "agegroup": "",
            "competition_ID": "12856527",
            "compName": "European Champion Clubs Cup Cross Country",
            "compShort": "ECCC",
            "date": "2015-02-01",
            "city": "Guadalajara",
            "venuecountry": "ESP"
        },
        {
            "IndoorOutdoor": "Outdoor",
            "event": "HM",
            "okForSB": true,
            "result": "1:13:56",
            "iaafpoints": "1050",
            "wind": "",
            "rank": "3",
            "round": "",
            "roundstage": "Final",
            "agegroup": "",
            "competition_ID": "12857494",
            "compName": "NN City Pier City Half-Marathon",
            "compShort": "City Pier City",
            "date": "2015-03-08",
            "city": "Den Haag",
            "venuecountry": "NED"
        },
        {
            "IndoorOutdoor": "Outdoor",
            "event": "10K",
            "okForSB": true,
            "result": "33:00",
            "iaafpoints": "1087",
            "wind": "",
            "rank": "1",
            "round": "",
            "roundstage": "Final",
            "agegroup": "",
            "competition_ID": "12859310",
            "compName": "National Championships 10 km Road",
            "compShort": "NC",
            "date": "2015-03-28",
            "city": "Uster",
            "venuecountry": "SUI"
        },
        {
            "IndoorOutdoor": "Outdoor",
            "event": "3000",
            "okForSB": true,
            "result": "9:42.92",
            "iaafpoints": "966",
            "wind": "",
            "rank": "2",
            "round": "",
            "roundstage": "Final",
            "agegroup": "",
            "competition_ID": "12901611",
            "compName": "Auffahrtsmeeting",
            "compShort": "rB",
            "date": "2015-05-14",
            "city": "Langenthal",
            "venuecountry": "SUI"
        },
        {
            "IndoorOutdoor": "Outdoor",
            "event": "3000",
            "okForSB": false,
            "result": "9:17.57",
            "iaafpoints": "",
            "wind": "",
            "rank": "1",
            "round": "",
            "roundstage": "Final",
            "agegroup": "",
            "competition_ID": "12860362",
            "compName": "Auffahrtsmeeting",
            "compShort": null,
            "date": "2015-05-14",
            "city": "Langenthal",
            "venuecountry": "SUI"
        },
        {
            "IndoorOutdoor": "Outdoor",
            "event": "3000S",
            "okForSB": true,
            "result": "9:40.63",
            "iaafpoints": "1142",
            "wind": "",
            "rank": "1",
            "round": "",
            "roundstage": "Final",
            "agegroup": "",
            "competition_ID": "12860604",
            "compName": "IFAM Outdoor, Putbosstadion",
            "compShort": "IFAM",
            "date": "2015-05-23",
            "city": "Oordegem",
            "venuecountry": "BEL"
        },
        {
            "IndoorOutdoor": "Outdoor",
            "event": "5000",
            "okForSB": true,
            "result": "15:56.09",
            "iaafpoints": "1057",
            "wind": "",
            "rank": "1",
            "round": "",
            "roundstage": "Final",
            "agegroup": "",
            "competition_ID": "12860879",
            "compName": "Mini-Internationales",
            "compShort": null,
            "date": "2015-05-27",
            "city": "Koblenz",
            "venuecountry": "GER"
        },
        {
            "IndoorOutdoor": "Outdoor",
            "event": "3000S",
            "okForSB": true,
            "result": "9:46.54",
            "iaafpoints": "1128",
            "wind": "",
            "rank": "10",
            "round": "",
            "roundstage": "Final",
            "agegroup": "",
            "competition_ID": "12861332",
            "compName": "Sainsbury's Birmingham Grand Prix, IAAF Diamond League, Alexander Stadium",
            "compShort": "Sainsbury's",
            "date": "2015-06-07",
            "city": "Birmingham",
            "venuecountry": "GBR"
        },
        {
            "IndoorOutdoor": "Outdoor",
            "event": "3000S",
            "okForSB": true,
            "result": "9:50.32",
            "iaafpoints": "1119",
            "wind": "",
            "rank": "2",
            "round": "",
            "roundstage": "Final",
            "agegroup": "",
            "competition_ID": "12861912",
            "compName": "6th European Athletics Team Championships, First League, Pankrition Stadium",
            "compShort": "ETC-1",
            "date": "2015-06-20",
            "city": "Ir\u00e1klio",
            "venuecountry": "GRE"
        },
        {
            "IndoorOutdoor": "Outdoor",
            "event": "3000S",
            "okForSB": true,
            "result": "10:01.20",
            "iaafpoints": "1092",
            "wind": "",
            "rank": "14",
            "round": "",
            "roundstage": "Final",
            "agegroup": "",
            "competition_ID": "12862441",
            "compName": "40th Athletissima, IAAF Diamond League",
            "compShort": "Athletissima",
            "date": "2015-07-09",
            "city": "Lausanne",
            "venuecountry": "SUI"
        },
        {
            "IndoorOutdoor": "Outdoor",
            "event": "CC",
            "okForSB": true,
            "result": "28:41",
            "iaafpoints": "",
            "wind": "",
            "rank": "14",
            "round": "",
            "roundstage": "Final",
            "agegroup": "",
            "competition_ID": "12866178",
            "compName": "International Loket Warandeloop",
            "compShort": "Warandeloop",
            "date": "2015-11-22",
            "city": "Tilburg",
            "venuecountry": "NED"
        },
        {
            "IndoorOutdoor": "Outdoor",
            "event": "CC",
            "okForSB": true,
            "result": "27:13",
            "iaafpoints": "",
            "wind": "",
            "rank": "31",
            "round": "",
            "roundstage": "Final",
            "agegroup": "",
            "competition_ID": "12866672",
            "compName": "22nd European Cross Country Championships",
            "compShort": "EC",
            "date": "2015-12-13",
            "city": "Hy\u00e8res",
            "venuecountry": "FRA"
        },
        {
            "IndoorOutdoor": "Indoor",
            "event": "3000",
            "okForSB": true,
            "result": "9:34.44",
            "iaafpoints": "1013",
            "wind": "",
            "rank": "1",
            "round": "",
            "roundstage": "Final",
            "agegroup": "",
            "competition_ID": "12870351",
            "compName": "National Indoor Championships",
            "compShort": "NC",
            "date": "2016-02-28",
            "city": "St. Gallen",
            "venuecountry": "SUI"
        },
        {
            "IndoorOutdoor": "Outdoor",
            "event": "HM",
            "okForSB": true,
            "result": "1:14:40",
            "iaafpoints": "1036",
            "wind": "",
            "rank": "6",
            "round": "",
            "roundstage": "Final",
            "agegroup": "",
            "competition_ID": "12871252",
            "compName": "45th Stramilano Agonistica Internazionale",
            "compShort": "Stramilano",
            "date": "2016-03-20",
            "city": "Milano",
            "venuecountry": "ITA"
        },
        {
            "IndoorOutdoor": "Outdoor",
            "event": "RR",
            "okForSB": true,
            "result": "13:44",
            "iaafpoints": "",
            "wind": "",
            "rank": "3",
            "round": "",
            "roundstage": "Final",
            "agegroup": "",
            "competition_ID": "12873227",
            "compName": "Luzerner Stadtlauf",
            "compShort": null,
            "date": "2016-04-30",
            "city": "Luzern",
            "venuecountry": "SUI"
        },
        {
            "IndoorOutdoor": "Outdoor",
            "event": "3000",
            "okForSB": true,
            "result": "9:21.45",
            "iaafpoints": "1035",
            "wind": "",
            "rank": "",
            "round": "",
            "roundstage": "Final",
            "agegroup": "",
            "competition_ID": "12872998",
            "compName": "Auffahrtsmeeting",
            "compShort": null,
            "date": "2016-05-05",
            "city": "Langenthal",
            "venuecountry": "SUI"
        },
        {
            "IndoorOutdoor": "Outdoor",
            "event": "2000S",
            "okForSB": true,
            "result": "6:29.15",
            "iaafpoints": "1071",
            "wind": "",
            "rank": "1",
            "round": "",
            "roundstage": "Final",
            "agegroup": "",
            "competition_ID": "12873126",
            "compName": "26th Internationales L\u00e4ufermeeting, Sch\u00f6nbuchstadion",
            "compShort": null,
            "date": "2016-05-08",
            "city": "Pliezhausen",
            "venuecountry": "GER"
        },
        {
            "IndoorOutdoor": "Outdoor",
            "event": "3000S",
            "okForSB": true,
            "result": "9:49.55",
            "iaafpoints": "1120",
            "wind": "",
            "rank": "3",
            "round": "",
            "roundstage": "Final",
            "agegroup": "",
            "competition_ID": "12875520",
            "compName": "Hamburg Run Fun Day",
            "compShort": null,
            "date": "2016-05-22",
            "city": "Hamburg",
            "venuecountry": "GER"
        },
        {
            "IndoorOutdoor": "Outdoor",
            "event": "2000S",
            "okForSB": true,
            "result": "6:20.67",
            "iaafpoints": "1105",
            "wind": "",
            "rank": "1",
            "round": "",
            "roundstage": "Final",
            "agegroup": "",
            "competition_ID": "12873974",
            "compName": null,
            "compShort": null,
            "date": "2016-05-27",
            "city": "Uster",
            "venuecountry": "SUI"
        },
        {
            "IndoorOutdoor": "Outdoor",
            "event": "5K",
            "okForSB": true,
            "result": "16:24",
            "iaafpoints": "1006",
            "wind": "",
            "rank": "2",
            "round": "",
            "roundstage": "Final",
            "agegroup": "",
            "competition_ID": "12875727",
            "compName": "Schweizer Frauenlauf 5-K",
            "compShort": null,
            "date": "2016-06-12",
            "city": "Bern",
            "venuecountry": "SUI"
        },
        {
            "IndoorOutdoor": "Outdoor",
            "event": "3000S",
            "okForSB": true,
            "result": "9:53.61",
            "iaafpoints": "1111",
            "wind": "",
            "rank": "1",
            "round": "",
            "roundstage": "Final",
            "agegroup": "",
            "competition_ID": "12875495",
            "compName": "Spitzen Leichtathletik, Stadion Allmend",
            "compShort": "Spitzen",
            "date": "2016-06-14",
            "city": "Luzern",
            "venuecountry": "SUI"
        },
        {
            "IndoorOutdoor": "Outdoor",
            "event": "1500",
            "okForSB": true,
            "result": "4:25.58",
            "iaafpoints": "1009",
            "wind": "",
            "rank": "1",
            "round": "",
            "roundstage": "Final",
            "agegroup": "",
            "competition_ID": "12876206",
            "compName": "Bonus-Track Swiss Meeting 2016",
            "compShort": null,
            "date": "2016-07-02",
            "city": "Nottwil",
            "venuecountry": "SUI"
        },
        {
            "IndoorOutdoor": "Outdoor",
            "event": "3000S",
            "okForSB": true,
            "result": "9:40.28",
            "iaafpoints": "1143",
            "wind": "",
            "rank": "2",
            "round": "h2",
            "roundstage": "Prelim",
            "agegroup": "",
            "competition_ID": "12876245",
            "compName": "23rd European Athletics Championships",
            "compShort": "EC",
            "date": "2016-07-08",
            "city": "Amsterdam",
            "venuecountry": "NED"
        },
        {
            "IndoorOutdoor": "Outdoor",
            "event": "3000S",
            "okForSB": true,
            "result": "9:40.01",
            "iaafpoints": "1144",
            "wind": "",
            "rank": "5",
            "round": "",
            "roundstage": "Final",
            "agegroup": "",
            "competition_ID": "12876245",
            "compName": "23rd European Athletics Championships",
            "compShort": "EC",
            "date": "2016-07-10",
            "city": "Amsterdam",
            "venuecountry": "NED"
        },
        {
            "IndoorOutdoor": "Outdoor",
            "event": "5000",
            "okForSB": true,
            "result": "16:27.38",
            "iaafpoints": "1000",
            "wind": "",
            "rank": "1",
            "round": "",
            "roundstage": "Final",
            "agegroup": "",
            "competition_ID": "12876713",
            "compName": "National Championships",
            "compShort": "NC",
            "date": "2016-07-16",
            "city": "Gen\u00e8ve",
            "venuecountry": "SUI"
        },
        {
            "IndoorOutdoor": "Outdoor",
            "event": "1500",
            "okForSB": true,
            "result": "4:40.50",
            "iaafpoints": "902",
            "wind": "",
            "rank": "3",
            "round": "h2",
            "roundstage": "Prelim",
            "agegroup": "",
            "competition_ID": "12876713",
            "compName": "National Championships",
            "compShort": "NC",
            "date": "2016-07-16",
            "city": "Gen\u00e8ve",
            "venuecountry": "SUI"
        },
        {
            "IndoorOutdoor": "Outdoor",
            "event": "1500",
            "okForSB": true,
            "result": "4:31.73",
            "iaafpoints": "964",
            "wind": "",
            "rank": "1",
            "round": "",
            "roundstage": "Final",
            "agegroup": "",
            "competition_ID": "12876713",
            "compName": "National Championships",
            "compShort": "NC",
            "date": "2016-07-17",
            "city": "Gen\u00e8ve",
            "venuecountry": "SUI"
        },
        {
            "IndoorOutdoor": "Outdoor",
            "event": "3000S",
            "okForSB": true,
            "result": "9:30.54",
            "iaafpoints": "1167",
            "wind": "",
            "rank": "6",
            "round": "h2",
            "roundstage": "Prelim",
            "agegroup": "",
            "competition_ID": "12877460",
            "compName": "31st Olympic Games",
            "compShort": "OG",
            "date": "2016-08-13",
            "city": "Rio de Janeiro",
            "venuecountry": "BRA"
        },
        {
            "IndoorOutdoor": "Outdoor",
            "event": "3000S",
            "okForSB": true,
            "result": "9:59.30",
            "iaafpoints": "1097",
            "wind": "",
            "rank": "18",
            "round": "",
            "roundstage": "Final",
            "agegroup": "",
            "competition_ID": "12877460",
            "compName": "31st Olympic Games",
            "compShort": "OG",
            "date": "2016-08-15",
            "city": "Rio de Janeiro",
            "venuecountry": "BRA"
        },
        {
            "IndoorOutdoor": "Outdoor",
            "event": "3000S",
            "okForSB": true,
            "result": "9:45.88",
            "iaafpoints": "1129",
            "wind": "",
            "rank": "13",
            "round": "",
            "roundstage": "Final",
            "agegroup": "",
            "competition_ID": "12877790",
            "compName": "29th Weltklasse, IAAF Diamond League, Stadion Letzigrund (W Pole vault Hauptbahnhof)",
            "compShort": "WK",
            "date": "2016-09-01",
            "city": "Z\u00fcrich",
            "venuecountry": "SUI"
        },
        {
            "IndoorOutdoor": "Outdoor",
            "event": "RR",
            "okForSB": true,
            "result": "19:30",
            "iaafpoints": "",
            "wind": "",
            "rank": "1",
            "round": "",
            "roundstage": "Final",
            "agegroup": "",
            "competition_ID": "12879254",
            "compName": "La Corrida Bulloise",
            "compShort": null,
            "date": "2016-11-19",
            "city": "Bulle",
            "venuecountry": "SUI"
        },
        {
            "IndoorOutdoor": "Outdoor",
            "event": "CC",
            "okForSB": true,
            "result": "27:16",
            "iaafpoints": "",
            "wind": "",
            "rank": "1",
            "round": "",
            "roundstage": "Final",
            "agegroup": "",
            "competition_ID": "12879823",
            "compName": "International Warandecross",
            "compShort": "Warandecross",
            "date": "2016-11-27",
            "city": "Tilburg",
            "venuecountry": "NED"
        },
        {
            "IndoorOutdoor": "Outdoor",
            "event": "CC",
            "okForSB": true,
            "result": "25.46",
            "iaafpoints": "",
            "wind": "",
            "rank": "8",
            "round": "",
            "roundstage": "Final",
            "agegroup": "",
            "competition_ID": "12880180",
            "compName": "23rd European Cross Country Championships",
            "compShort": "EC",
            "date": "2016-12-11",
            "city": "Chia",
            "venuecountry": "ITA"
        },
        {
            "IndoorOutdoor": "Outdoor",
            "event": "10K",
            "okForSB": true,
            "result": "32:10",
            "iaafpoints": "1130",
            "wind": "",
            "rank": "1",
            "round": "",
            "roundstage": "Final",
            "agegroup": "",
            "competition_ID": "12889494",
            "compName": "10km de Payerne",
            "compShort": null,
            "date": "2017-02-26",
            "city": "Payerne",
            "venuecountry": "SUI"
        },
        {
            "IndoorOutdoor": "Outdoor",
            "event": "HM",
            "okForSB": true,
            "result": "1:10:17",
            "iaafpoints": "1124",
            "wind": "",
            "rank": "1",
            "round": "",
            "roundstage": "Final",
            "agegroup": "",
            "competition_ID": "12889957",
            "compName": null,
            "compShort": null,
            "date": "2017-03-12",
            "city": "Den Haag",
            "venuecountry": "NED"
        },
        {
            "IndoorOutdoor": "Outdoor",
            "event": "5000",
            "okForSB": true,
            "result": "15:47.94",
            "iaafpoints": "1072",
            "wind": "",
            "rank": "1",
            "round": "",
            "roundstage": "Final",
            "agegroup": "",
            "competition_ID": "12892752",
            "compName": null,
            "compShort": null,
            "date": "2017-05-06",
            "city": "D\u00fcdingen",
            "venuecountry": "SUI"
        },
        {
            "IndoorOutdoor": "Outdoor",
            "event": "2000S",
            "okForSB": true,
            "result": "6:20.33",
            "iaafpoints": "1106",
            "wind": "",
            "rank": "1",
            "round": "",
            "roundstage": "Final",
            "agegroup": "",
            "competition_ID": "12893265",
            "compName": "27. Internationales L\u00e4ufermeeting",
            "compShort": null,
            "date": "2017-05-14",
            "city": "Pliezhausen",
            "venuecountry": "GER"
        },
        {
            "IndoorOutdoor": "Outdoor",
            "event": "3000S",
            "okForSB": true,
            "result": "9:40.36",
            "iaafpoints": "1143",
            "wind": "",
            "rank": "1",
            "round": "",
            "roundstage": "Final",
            "agegroup": "",
            "competition_ID": "12893528",
            "compName": "National Championships 10000m & 3000m steeple",
            "compShort": "NC",
            "date": "2017-05-19",
            "city": "Uster",
            "venuecountry": "SUI"
        },
        {
            "IndoorOutdoor": "Outdoor",
            "event": "3000S",
            "okForSB": true,
            "result": "9:26.86",
            "iaafpoints": "1176",
            "wind": "",
            "rank": "4",
            "round": "",
            "roundstage": "Final",
            "agegroup": "",
            "competition_ID": "12894641",
            "compName": "Meeting National 2 de Belfort Montb\u00e9liard",
            "compShort": null,
            "date": "2017-06-09",
            "city": "Belfort",
            "venuecountry": "FRA"
        },
        {
            "IndoorOutdoor": "Outdoor",
            "event": "5K",
            "okForSB": true,
            "result": "16:33",
            "iaafpoints": "990",
            "wind": "",
            "rank": "1",
            "round": "",
            "roundstage": "Final",
            "agegroup": "",
            "competition_ID": "12894756",
            "compName": "Schweizer Frauenlauf",
            "compShort": null,
            "date": "2017-06-11",
            "city": "Bern",
            "venuecountry": "SUI"
        },
        {
            "IndoorOutdoor": "Outdoor",
            "event": "3000S",
            "okForSB": true,
            "result": "9:21.65",
            "iaafpoints": "1189",
            "wind": "",
            "rank": "3",
            "round": "",
            "roundstage": "Final",
            "agegroup": "",
            "competition_ID": "12894847",
            "compName": "Bislett Games, IAAF Diamond League, Bislett Stadium",
            "compShort": "Bislett",
            "date": "2017-06-15",
            "city": "Oslo",
            "venuecountry": "NOR"
        },
        {
            "IndoorOutdoor": "Outdoor",
            "event": "3000S",
            "okForSB": true,
            "result": "9:38.08",
            "iaafpoints": "1148",
            "wind": "",
            "rank": "1",
            "round": "",
            "roundstage": "Final",
            "agegroup": "",
            "competition_ID": "12896371",
            "compName": "7th European Athletics Team Championships, First League, Karl's Stadium",
            "compShort": "ETC-1",
            "date": "2017-06-24",
            "city": "Vaasa",
            "venuecountry": "FIN"
        },
        {
            "IndoorOutdoor": "Outdoor",
            "event": "5000",
            "okForSB": true,
            "result": "15:47.29",
            "iaafpoints": "1073",
            "wind": "",
            "rank": "1",
            "round": "",
            "roundstage": "Final",
            "agegroup": "",
            "competition_ID": "12896371",
            "compName": "7th European Athletics Team Championships, First League, Karl's Stadium",
            "compShort": "ETC-1",
            "date": "2017-06-25",
            "city": "Vaasa",
            "venuecountry": "FIN"
        },
        {
            "IndoorOutdoor": "Outdoor",
            "event": "3000S",
            "okForSB": true,
            "result": "9:22.01",
            "iaafpoints": "1188",
            "wind": "",
            "rank": "8",
            "round": "",
            "roundstage": "Final",
            "agegroup": "",
            "competition_ID": "12896884",
            "compName": "Meeting Paris, IAAF Diamond League, Stade S\u00e9bastien Charl\u00e9ty",
            "compShort": "Meet Paris",
            "date": "2017-07-01",
            "city": "Paris",
            "venuecountry": "FRA"
        },
        {
            "IndoorOutdoor": "Outdoor",
            "event": "3000",
            "okForSB": true,
            "result": "8:58.63",
            "iaafpoints": "1110",
            "wind": "",
            "rank": "7",
            "round": "",
            "roundstage": "Final",
            "agegroup": "",
            "competition_ID": "12898045",
            "compName": "Spitzen Leichtathletik, Stadion Allmend",
            "compShort": "",
            "date": "2017-07-11",
            "city": "Luzern",
            "venuecountry": "SUI"
        },
        {
            "IndoorOutdoor": "Outdoor",
            "event": "800",
            "okForSB": true,
            "result": "2:12.07",
            "iaafpoints": "956",
            "wind": "",
            "rank": "1",
            "round": "h3",
            "roundstage": "Prelim",
            "agegroup": "",
            "competition_ID": "12898418",
            "compName": "National Championships",
            "compShort": "NC",
            "date": "2017-07-21",
            "city": "Z\u00fcrich",
            "venuecountry": "SUI"
        },
        {
            "IndoorOutdoor": "Outdoor",
            "event": "800",
            "okForSB": true,
            "result": "2:13.96",
            "iaafpoints": "926",
            "wind": "",
            "rank": "2",
            "round": "",
            "roundstage": "Final",
            "agegroup": "",
            "competition_ID": "12898418",
            "compName": "National Championships",
            "compShort": "NC",
            "date": "2017-07-22",
            "city": "Z\u00fcrich",
            "venuecountry": "SUI"
        },
        {
            "IndoorOutdoor": "Outdoor",
            "event": "3000S",
            "okForSB": true,
            "result": "9:36.08",
            "iaafpoints": "1153",
            "wind": "",
            "rank": "7",
            "round": "h3",
            "roundstage": "Prelim",
            "agegroup": "",
            "competition_ID": "12898707",
            "compName": "16th IAAF World Championships",
            "compShort": "WC",
            "date": "2017-08-09",
            "city": "London",
            "venuecountry": "GBR"
        },
        {
            "IndoorOutdoor": "Outdoor",
            "event": "3000S",
            "okForSB": true,
            "result": "9:28.80",
            "iaafpoints": "1171",
            "wind": "",
            "rank": "10",
            "round": "",
            "roundstage": "Final",
            "agegroup": "",
            "competition_ID": "12899125",
            "compName": "30th Weltklasse, IAAF Diamond League, Stadion Letzigrund (W Pole vault Hauptbahnhof)",
            "compShort": "WK",
            "date": "2017-08-24",
            "city": "Z\u00fcrich",
            "venuecountry": "SUI"
        },
        {
            "IndoorOutdoor": "Outdoor",
            "event": "RR",
            "okForSB": true,
            "result": "20:01",
            "iaafpoints": "",
            "wind": "",
            "rank": "2",
            "round": "",
            "roundstage": "Final",
            "agegroup": "",
            "competition_ID": "12900819",
            "compName": "La Corrida Bulloise",
            "compShort": null,
            "date": "2017-11-18",
            "city": "Bulle",
            "venuecountry": "SUI"
        },
        {
            "IndoorOutdoor": "Outdoor",
            "event": "CC",
            "okForSB": true,
            "result": "28:43",
            "iaafpoints": "",
            "wind": "",
            "rank": "2",
            "round": "",
            "roundstage": "Final",
            "agegroup": "",
            "competition_ID": "12900992",
            "compName": "loket.nl Warande Cross",
            "compShort": null,
            "date": "2017-11-26",
            "city": "Tilburg",
            "venuecountry": "NED"
        },
        {
            "IndoorOutdoor": "Outdoor",
            "event": "RR",
            "okForSB": true,
            "result": "24:23",
            "iaafpoints": "",
            "wind": "",
            "rank": "4",
            "round": "",
            "roundstage": "Final",
            "agegroup": "",
            "competition_ID": "12901454",
            "compName": "Course de l'Escalade",
            "compShort": null,
            "date": "2017-12-02",
            "city": "Gen\u00e8ve",
            "venuecountry": "SUI"
        },
        {
            "IndoorOutdoor": "Outdoor",
            "event": "CC",
            "okForSB": true,
            "result": "27:24",
            "iaafpoints": "",
            "wind": "",
            "rank": "7",
            "round": "",
            "roundstage": "Final",
            "agegroup": "",
            "competition_ID": "12901354",
            "compName": "24th European Cross Country Championships",
            "compShort": "EC",
            "date": "2017-12-10",
            "city": "\u0160amor\u00edn",
            "venuecountry": "SVK"
        },
        {
            "IndoorOutdoor": "Outdoor",
            "event": "HM",
            "okForSB": true,
            "result": "1:10:36",
            "iaafpoints": "1117",
            "wind": "",
            "rank": "16",
            "round": "",
            "roundstage": "Final",
            "agegroup": "",
            "competition_ID": "12905148",
            "compName": "IAAF World Half Marathon Championships",
            "compShort": "WC",
            "date": "2018-03-24",
            "city": "Valencia",
            "venuecountry": "ESP"
        },
        {
            "IndoorOutdoor": "Outdoor",
            "event": "5K",
            "okForSB": true,
            "result": "16:43",
            "iaafpoints": "972",
            "wind": "",
            "rank": "1",
            "round": "",
            "roundstage": "Final",
            "agegroup": "",
            "competition_ID": "12908443",
            "compName": "Schweizer Frauenlauf 5K",
            "compShort": null,
            "date": "2018-06-10",
            "city": "Bern",
            "venuecountry": "SUI"
        },
        {
            "IndoorOutdoor": "Outdoor",
            "event": "3000S",
            "okForSB": true,
            "result": "9:39.89",
            "iaafpoints": "1144",
            "wind": "",
            "rank": "10",
            "round": "",
            "roundstage": "Final",
            "agegroup": "",
            "competition_ID": "12909661",
            "compName": "Meeting Paris, IAAF Diamond League, Stade S\u00e9bastien Charl\u00e9ty",
            "compShort": "Meet Paris",
            "date": "2018-06-30",
            "city": "Paris",
            "venuecountry": "FRA"
        },
        {
            "IndoorOutdoor": "Outdoor",
            "event": "3000S",
            "okForSB": true,
            "result": "9:40.73",
            "iaafpoints": "1142",
            "wind": "",
            "rank": "4",
            "round": "",
            "roundstage": "Final",
            "agegroup": "",
            "competition_ID": "12910462",
            "compName": "Spitzen Leichtathletik, Stadion Allmend",
            "compShort": "Spitzen",
            "date": "2018-07-09",
            "city": "Luzern",
            "venuecountry": "SUI"
        },
        {
            "IndoorOutdoor": "Outdoor",
            "event": "1500",
            "okForSB": true,
            "result": "4:17.91",
            "iaafpoints": "1066",
            "wind": "",
            "rank": "1",
            "round": "",
            "roundstage": "Final",
            "agegroup": "",
            "competition_ID": "12910595",
            "compName": "SM Leichtathletik Aktive",
            "compShort": "NC",
            "date": "2018-07-14",
            "city": "Zofingen",
            "venuecountry": "SUI"
        },
        {
            "IndoorOutdoor": "Outdoor",
            "event": "5000",
            "okForSB": true,
            "result": "15:23.44",
            "iaafpoints": "1118",
            "wind": "",
            "rank": "5",
            "round": "",
            "roundstage": "Final",
            "agegroup": "",
            "competition_ID": "12910726",
            "compName": "Gal\u00e0 dei Castelli, Stadio Comunale",
            "compShort": null,
            "date": "2018-07-18",
            "city": "Bellinzona",
            "venuecountry": "SUI"
        },
        {
            "IndoorOutdoor": "Outdoor",
            "event": "3000S",
            "okForSB": true,
            "result": "9:32.32",
            "iaafpoints": "1163",
            "wind": "",
            "rank": "1",
            "round": "h2",
            "roundstage": "Prelim",
            "agegroup": "",
            "competition_ID": "12911200",
            "compName": "24th European Athletics Championships",
            "compShort": "EC",
            "date": "2018-08-10",
            "city": "Berlin",
            "venuecountry": "GER"
        },
        {
            "IndoorOutdoor": "Outdoor",
            "event": "3000S",
            "okForSB": true,
            "result": "9:22.29",
            "iaafpoints": "1188",
            "wind": "",
            "rank": "2",
            "round": "",
            "roundstage": "Final",
            "agegroup": "",
            "competition_ID": "12911200",
            "compName": "24th European Athletics Championships",
            "compShort": "EC",
            "date": "2018-08-12",
            "city": "Berlin",
            "venuecountry": "GER"
        },
        {
            "IndoorOutdoor": "Outdoor",
            "event": "1500",
            "okForSB": true,
            "result": "4:17.33",
            "iaafpoints": "1070",
            "wind": "",
            "rank": "1",
            "round": "",
            "roundstage": "Final",
            "agegroup": "",
            "competition_ID": "12911526",
            "compName": "Abendmeeting",
            "compShort": null,
            "date": "2018-08-18",
            "city": "Regensdorf",
            "venuecountry": "SUI"
        },
        {
            "IndoorOutdoor": "Outdoor",
            "event": "HM",
            "okForSB": true,
            "result": "1:15:30",
            "iaafpoints": "1019",
            "wind": "",
            "rank": "1",
            "round": "",
            "roundstage": "Final",
            "agegroup": "",
            "competition_ID": "12912335",
            "compName": "Greifenseelauf Half-Marathon",
            "compShort": null,
            "date": "2018-09-22",
            "city": "Z\u00fcrich",
            "venuecountry": "SUI"
        },
        {
            "IndoorOutdoor": "Outdoor",
            "event": "10K",
            "okForSB": true,
            "result": "32:01",
            "iaafpoints": "1138",
            "wind": "",
            "rank": "3",
            "round": "",
            "roundstage": "Final",
            "agegroup": "",
            "competition_ID": "12912690",
            "compName": "Bridgestone Great 10K Berlin",
            "compShort": null,
            "date": "2018-10-14",
            "city": "Berlin",
            "venuecountry": "GER"
        },
        {
            "IndoorOutdoor": "Outdoor",
            "event": "RR",
            "okForSB": true,
            "result": "19:42",
            "iaafpoints": "",
            "wind": "",
            "rank": "1",
            "round": "",
            "roundstage": "Final",
            "agegroup": "",
            "competition_ID": "12913827",
            "compName": "43rd La Corrida Bulloise",
            "compShort": null,
            "date": "2018-11-17",
            "city": "Bulle",
            "venuecountry": "SUI"
        },
        {
            "IndoorOutdoor": "Outdoor",
            "event": "CC",
            "okForSB": true,
            "result": "26.37",
            "iaafpoints": "",
            "wind": "",
            "rank": "1",
            "round": "",
            "roundstage": "Final",
            "agegroup": "",
            "competition_ID": "12913711",
            "compName": "Vidiled Warandeloop",
            "compShort": "Warandeloop",
            "date": "2018-11-25",
            "city": "Tilburg",
            "venuecountry": "NED"
        },
        {
            "IndoorOutdoor": "Outdoor",
            "event": "CC",
            "okForSB": true,
            "result": "26:06",
            "iaafpoints": "",
            "wind": "",
            "rank": "2",
            "round": "",
            "roundstage": "Final",
            "agegroup": "",
            "competition_ID": "12914471",
            "compName": "25th European Cross Country Championships",
            "compShort": "EC",
            "date": "2018-12-09",
            "city": "Tilburg",
            "venuecountry": "NED"
        },
        {
            "IndoorOutdoor": "Outdoor",
            "event": "10K",
            "okForSB": true,
            "result": "32:04",
            "iaafpoints": "1136",
            "wind": "",
            "rank": "1",
            "round": "",
            "roundstage": "Final",
            "agegroup": "",
            "competition_ID": "12919207",
            "compName": "10K de Payerne",
            "compShort": null,
            "date": "2019-03-03",
            "city": "Payerne",
            "venuecountry": "SUI"
        },
        {
            "IndoorOutdoor": "Outdoor",
            "event": "10K",
            "okForSB": false,
            "result": "32:10",
            "iaafpoints": "",
            "wind": "",
            "rank": "1",
            "round": "",
            "roundstage": "Final",
            "agegroup": "",
            "competition_ID": "12925119",
            "compName": "10KM SM",
            "compShort": "NC",
            "date": "2019-03-23",
            "city": "Uster",
            "venuecountry": "SUI"
        },
        {
            "IndoorOutdoor": "Outdoor",
            "event": "10K",
            "okForSB": true,
            "result": "34:30",
            "iaafpoints": "1010",
            "wind": "",
            "rank": "2",
            "round": "",
            "roundstage": "Final",
            "agegroup": "",
            "competition_ID": "12958499",
            "compName": "10K de Payerne",
            "compShort": null,
            "date": "2020-02-23",
            "city": "Payerne",
            "venuecountry": "SUI"
        },
        {
            "IndoorOutdoor": "Outdoor",
            "event": "10K",
            "okForSB": true,
            "result": "33:30",
            "iaafpoints": "1061",
            "wind": "",
            "rank": "2",
            "round": "",
            "roundstage": "Final",
            "agegroup": "",
            "competition_ID": "",
            "compName": null,
            "compShort": null,
            "date": "2020-02-23",
            "city": "Payerne",
            "venuecountry": "SUI"
        },
        {
            "IndoorOutdoor": "Outdoor",
            "event": "5000",
            "okForSB": false,
            "result": "15:54.28",
            "iaafpoints": "",
            "wind": "",
            "rank": "4",
            "round": "",
            "roundstage": "Final",
            "agegroup": "",
            "competition_ID": "12963831",
            "compName": null,
            "compShort": null,
            "date": "2020-06-16",
            "city": "Wetzikon",
            "venuecountry": "SUI"
        },
        {
            "IndoorOutdoor": "Outdoor",
            "event": "10000",
            "okForSB": false,
            "result": "32:16.37",
            "iaafpoints": "",
            "wind": "",
            "rank": "2",
            "round": "",
            "roundstage": "Final",
            "agegroup": "",
            "competition_ID": "12964681",
            "compName": "SM 10,000m/Steeple // UsterRunning",
            "compShort": null,
            "date": "2020-06-26",
            "city": "Uster",
            "venuecountry": "SUI"
        },
        {
            "IndoorOutdoor": "Outdoor",
            "event": "5000",
            "okForSB": false,
            "result": "15:17.27",
            "iaafpoints": "",
            "wind": "",
            "rank": "1",
            "round": "",
            "roundstage": "Final",
            "agegroup": "",
            "competition_ID": "12968312",
            "compName": "Abendmeeting ",
            "compShort": null,
            "date": "2020-08-08",
            "city": "Regensdorf",
            "venuecountry": "SUI"
        },
        {
            "IndoorOutdoor": "Outdoor",
            "event": "5000",
            "okForSB": false,
            "result": "15:10.31",
            "iaafpoints": "",
            "wind": "",
            "rank": "1",
            "round": "",
            "roundstage": "Final",
            "agegroup": "",
            "competition_ID": "12969203",
            "compName": "Championnat Fribourgeois 5000m OPEN",
            "compShort": null,
            "date": "2020-08-21",
            "city": "Bulle",
            "venuecountry": "SUI"
        },
        {
            "IndoorOutdoor": "Outdoor",
            "event": "1500",
            "okForSB": true,
            "result": "4:29.13",
            "iaafpoints": "983",
            "wind": "",
            "rank": "1",
            "round": "h3",
            "roundstage": "Prelim",
            "agegroup": "",
            "competition_ID": "12970465",
            "compName": "SM Aktive",
            "compShort": "NC",
            "date": "2020-09-11",
            "city": "Basel",
            "venuecountry": "SUI"
        },
        {
            "IndoorOutdoor": "Outdoor",
            "event": "5000",
            "okForSB": true,
            "result": "16:30.18",
            "iaafpoints": "995",
            "wind": "",
            "rank": "1",
            "round": "",
            "roundstage": "Final",
            "agegroup": "",
            "competition_ID": "12970465",
            "compName": "SM Aktive",
            "compShort": "NC",
            "date": "2020-09-11",
            "city": "Basel",
            "venuecountry": "SUI"
        },
        {
            "IndoorOutdoor": "Outdoor",
            "event": "1500",
            "okForSB": true,
            "result": "4:14.29",
            "iaafpoints": "1093",
            "wind": "",
            "rank": "1",
            "round": "",
            "roundstage": "Final",
            "agegroup": "",
            "competition_ID": "12970465",
            "compName": "SM Aktive",
            "compShort": "NC",
            "date": "2020-09-12",
            "city": "Basel",
            "venuecountry": "SUI"
        },
        {
            "IndoorOutdoor": "Outdoor",
            "event": "10K",
            "okForSB": true,
            "result": "32:23",
            "iaafpoints": "1119",
            "wind": "",
            "rank": "1",
            "round": "",
            "roundstage": "Final",
            "agegroup": "",
            "competition_ID": "12971368",
            "compName": "Swiss championships 10 km road race",
            "compShort": "NC",
            "date": "2020-09-27",
            "city": "Belp",
            "venuecountry": "SUI"
        },
        {
            "IndoorOutdoor": "Outdoor",
            "event": "HM",
            "okForSB": true,
            "result": "1:08:38",
            "iaafpoints": "1158",
            "wind": "",
            "rank": "13",
            "round": "",
            "roundstage": "Final",
            "agegroup": "",
            "competition_ID": "12972975",
            "compName": "World Athletics Half Marathon Championships",
            "compShort": "WC",
            "date": "2020-10-17",
            "city": "Gdynia",
            "venuecountry": "POL"
        },
        {
            "IndoorOutdoor": "Outdoor",
            "event": "HM",
            "okForSB": true,
            "result": "1:08:27",
            "iaafpoints": "1162",
            "wind": "",
            "rank": "1",
            "round": "",
            "roundstage": "Final",
            "agegroup": "",
            "competition_ID": "12978382",
            "compName": "itelligence Citylauf Invitational",
            "compShort": "",
            "date": "2021-03-21",
            "city": "Dresden",
            "venuecountry": "GER"
        },
        {
            "IndoorOutdoor": "Outdoor",
            "event": "Mar",
            "okForSB": true,
            "result": "2:26:14",
            "iaafpoints": "1153",
            "wind": "",
            "rank": "2",
            "round": "",
            "roundstage": "Final",
            "agegroup": "",
            "competition_ID": "12979500",
            "compName": "National Championship",
            "compShort": "NC",
            "date": "2021-04-03",
            "city": "Bern",
            "venuecountry": "SUI"
        },
        {
            "IndoorOutdoor": "Outdoor",
            "event": "10000",
            "okForSB": true,
            "result": "33:13.63",
            "iaafpoints": "1075",
            "wind": "",
            "rank": "1",
            "round": "",
            "roundstage": "Final",
            "agegroup": "",
            "competition_ID": "12988096",
            "compName": "SM 10'000m und Steeple",
            "compShort": "NC",
            "date": "2021-06-04",
            "city": "Uster",
            "venuecountry": "SUI"
        },
        {
            "IndoorOutdoor": "Outdoor",
            "event": "5000",
            "okForSB": true,
            "result": "15:42.45",
            "iaafpoints": "1082",
            "wind": "",
            "rank": "1",
            "round": "",
            "roundstage": "Final",
            "agegroup": "",
            "competition_ID": "12989741",
            "compName": "European Athletics Team Championships 1st League",
            "compShort": "ETC-1",
            "date": "2021-06-20",
            "city": "Cluj-Napoca",
            "venuecountry": "ROU"
        },
        {
            "IndoorOutdoor": "Outdoor",
            "event": "3000S",
            "okForSB": false,
            "result": "",
            "iaafpoints": "",
            "wind": "",
            "rank": "",
            "round": "",
            "roundstage": "Final",
            "agegroup": "",
            "competition_ID": "12990860",
            "compName": "Spitzen Leichtathletik",
            "compShort": "Spitzen",
            "date": "2021-06-29",
            "city": "Luzern",
            "venuecountry": "SUI"
        },
        {
            "IndoorOutdoor": "Outdoor",
            "event": "Mar",
            "okForSB": true,
            "result": "2:31:36",
            "iaafpoints": "1102",
            "wind": "",
            "rank": "12",
            "round": "",
            "roundstage": "Final",
            "agegroup": "",
            "competition_ID": "12992925",
            "compName": "32nd Olympic Games",
            "compShort": "OG",
            "date": "2021-08-07",
            "city": "Sapporo",
            "venuecountry": "JPN"
        },
        {
            "IndoorOutdoor": "Outdoor",
            "event": "Mar",
            "okForSB": true,
            "result": "2:26:31",
            "iaafpoints": "1150",
            "wind": "",
            "rank": "4",
            "round": "",
            "roundstage": "Final",
            "agegroup": "",
            "competition_ID": "12995213",
            "compName": "Vienna City Marathon (37th)",
            "compShort": null,
            "date": "2021-09-12",
            "city": "Wien",
            "venuecountry": "AUT"
        },
        {
            "IndoorOutdoor": "Outdoor",
            "event": "RR",
            "okForSB": true,
            "result": "24:51",
            "iaafpoints": "",
            "wind": "",
            "rank": "6",
            "round": "",
            "roundstage": "Final",
            "agegroup": "",
            "competition_ID": "12998885",
            "compName": "43rd Course de l'Escalade",
            "compShort": null,
            "date": "2021-12-05",
            "city": "Gen\u00e8ve",
            "venuecountry": "SUI"
        },
        {
            "IndoorOutdoor": "Outdoor",
            "event": "RR",
            "okForSB": true,
            "result": "15:49",
            "iaafpoints": "",
            "wind": "",
            "rank": "4",
            "round": "",
            "roundstage": "Final",
            "agegroup": "",
            "competition_ID": "12999156",
            "compName": "Course de No\u00ebl 52nd",
            "compShort": null,
            "date": "2021-12-11",
            "city": "Sion",
            "venuecountry": "SUI"
        },
        {
            "IndoorOutdoor": "Outdoor",
            "event": "10K",
            "okForSB": true,
            "result": "33:41",
            "iaafpoints": "1052",
            "wind": "",
            "rank": "1",
            "round": "",
            "roundstage": "Final",
            "agegroup": "",
            "competition_ID": "13031098",
            "compName": "Lauerzerseelauf Seewen",
            "compShort": null,
            "date": "2022-06-24",
            "city": "Seewen",
            "venuecountry": "SUI"
        },
        {
            "IndoorOutdoor": "Outdoor",
            "event": "Mar",
            "okForSB": true,
            "result": "2:30:17",
            "iaafpoints": "1115",
            "wind": "",
            "rank": "9",
            "round": "",
            "roundstage": "Final",
            "agegroup": "",
            "competition_ID": "13002371",
            "compName": "25th European Athletics Championships",
            "compShort": "EC",
            "date": "2022-08-15",
            "city": "M\u00fcnchen",
            "venuecountry": "GER"
        },
        {
            "IndoorOutdoor": "Outdoor",
            "event": "RR",
            "okForSB": true,
            "result": "24:33",
            "iaafpoints": "",
            "wind": "",
            "rank": "9",
            "round": "",
            "roundstage": "Final",
            "agegroup": "",
            "competition_ID": "13024448",
            "compName": "Course de l'Escalade",
            "compShort": null,
            "date": "2022-12-04",
            "city": "Gen\u00e8ve",
            "venuecountry": "SUI"
        },
        {
            "IndoorOutdoor": "Outdoor",
            "event": "5K",
            "okForSB": true,
            "result": "15:47",
            "iaafpoints": "1074",
            "wind": "",
            "rank": "7",
            "round": "",
            "roundstage": "Final",
            "agegroup": "",
            "competition_ID": "13024808",
            "compName": "Course de No\u00ebl",
            "compShort": null,
            "date": "2022-12-10",
            "city": "Sion",
            "venuecountry": "SUI"
        },
        {
            "IndoorOutdoor": "Outdoor",
            "event": "5K",
            "okForSB": true,
            "result": "16:36",
            "iaafpoints": "984",
            "wind": "",
            "rank": "3  ",
            "round": "",
            "roundstage": "Final",
            "agegroup": "",
            "competition_ID": "13044860",
            "compName": "Schweizer Frauenlauf 5-K (36th)",
            "compShort": null,
            "date": "2023-06-11",
            "city": "Bern",
            "venuecountry": "SUI"
        },
        {
            "IndoorOutdoor": "Outdoor",
            "event": "5000",
            "okForSB": true,
            "result": "16:18.16",
            "iaafpoints": "1016",
            "wind": "",
            "rank": "1",
            "round": "",
            "roundstage": "Final",
            "agegroup": "",
            "competition_ID": "13045895",
            "compName": "National Championships",
            "compShort": "NC",
            "date": "2023-07-29",
            "city": "Bellinzona",
            "venuecountry": "SUI"
        },
        {
            "IndoorOutdoor": "Outdoor",
            "event": "RR",
            "okForSB": true,
            "result": "1:34:56",
            "iaafpoints": "",
            "wind": "",
            "rank": "1",
            "round": "",
            "roundstage": "Final",
            "agegroup": "",
            "competition_ID": "13049911",
            "compName": "St. Moritz Running Festival / Engadiner Sommerlauf",
            "compShort": null,
            "date": "2023-08-13",
            "city": "Sils-St. Moritz",
            "venuecountry": "SUI"
        },
        {
            "IndoorOutdoor": "Outdoor",
            "event": "Mar",
            "okForSB": true,
            "result": "2:25:27",
            "iaafpoints": "1160",
            "wind": "",
            "rank": "15",
            "round": "",
            "roundstage": "Final",
            "agegroup": "",
            "competition_ID": "13048365",
            "compName": "BMW Berlin Marathon",
            "compShort": null,
            "date": "2023-09-24",
            "city": "Berlin",
            "venuecountry": "GER"
        },
        {
            "IndoorOutdoor": "Outdoor",
            "event": "Mar",
            "okForSB": true,
            "result": "2:24:30",
            "iaafpoints": "1169",
            "wind": "",
            "rank": "13",
            "round": "",
            "roundstage": "Final",
            "agegroup": "",
            "competition_ID": "13050767",
            "compName": "Maraton Valencia Trinidad Alfonso",
            "compShort": null,
            "date": "2023-12-03",
            "city": "Valencia",
            "venuecountry": "ESP"
        },
        {
            "IndoorOutdoor": "Outdoor",
            "event": "HM",
            "okForSB": true,
            "result": "1:13:10",
            "iaafpoints": "1065",
            "wind": "",
            "rank": "6",
            "round": "",
            "roundstage": "Final",
            "agegroup": "",
            "competition_ID": "13052782",
            "compName": "NN Egmond Halve Marathon",
            "compShort": null,
            "date": "2024-01-14",
            "city": "Egmond Aan Zee",
            "venuecountry": "NED"
        },
        {
            "IndoorOutdoor": "Outdoor",
            "event": "10K",
            "okForSB": true,
            "result": "32:52",
            "iaafpoints": "1094",
            "wind": "",
            "rank": "3",
            "round": "",
            "roundstage": "Final",
            "agegroup": "",
            "competition_ID": "13057208",
            "compName": "10km De Payerne",
            "compShort": null,
            "date": "2024-03-03",
            "city": "Payerne",
            "venuecountry": "SUI"
        },
        {
            "IndoorOutdoor": "Outdoor",
            "event": "HM",
            "okForSB": true,
            "result": "1:12:21",
            "iaafpoints": "1082",
            "wind": "",
            "rank": "8",
            "round": "",
            "roundstage": "Final",
            "agegroup": "",
            "competition_ID": "13058597",
            "compName": "United Airlines Nyc Half",
            "compShort": null,
            "date": "2024-03-17",
            "city": "New York NY",
            "venuecountry": "USA"
        },
        {
            "IndoorOutdoor": "Outdoor",
            "event": "10M",
            "okForSB": true,
            "result": "54:31",
            "iaafpoints": "1076",
            "wind": "",
            "rank": "1",
            "round": "",
            "roundstage": "Final",
            "agegroup": "",
            "competition_ID": "13088073",
            "compName": "Grand-Prix von Bern",
            "compShort": null,
            "date": "2024-05-18",
            "city": "Bern",
            "venuecountry": "SUI"
        },
        {
            "IndoorOutdoor": "Outdoor",
            "event": "HM",
            "okForSB": true,
            "result": "1:10:01",
            "iaafpoints": "1129",
            "wind": "",
            "rank": "7",
            "round": "",
            "roundstage": "Final",
            "agegroup": "",
            "competition_ID": "13075167",
            "compName": "26th European Athletics Championships",
            "compShort": "EC",
            "date": "2024-06-09",
            "city": "Roma",
            "venuecountry": "ITA"
        }
    ]
}